coverage_threshold/__init__.py
coverage_threshold/__main__.py
coverage_threshold/cli/__init__.py
coverage_threshold/cli/args.py
coverage_threshold/cli/colors.py
coverage_threshold/cli/main.py
coverage_threshold/cli/read_config.py
coverage_threshold/cli/read_report.py
coverage_threshold/lib/__init__.py
coverage_threshold/lib/_all_checks.py
coverage_threshold/lib/_common.py
coverage_threshold/lib/_file.py
coverage_threshold/lib/_totals.py
coverage_threshold/lib/alternative.py
coverage_threshold/lib/check_result.py
coverage_threshold/model/__init__.py
coverage_threshold/model/config.py
coverage_threshold/model/report.py
coverage_threshold/model/util.py
coverage_threshold-0.6.2.dist-info/METADATA
coverage_threshold-0.6.2.dist-info/WHEEL
coverage_threshold-0.6.2.dist-info/entry_points.txt
coverage_threshold-0.6.2.dist-info/licenses/LICENSE
coverage_threshold-0.6.2.dist-info/RECORD
