Metadata-Version: 2.4
Name: coverage_threshold
Version: 0.6.2
Summary: Tools for coverage threshold limits
Project-URL: Homepage, https://github.com/DeanWay/coverage-threshold
Project-URL: Issues, https://github.com/DeanWay/coverage-threshold/issues
Author-email: Dean Way <deanwaydev@gmail.com>
License-Expression: MIT
License-File: LICENSE
Classifier: License :: OSI Approved :: MIT License
Classifier: Operating System :: OS Independent
Classifier: Programming Language :: Python :: 3.7
Classifier: Programming Language :: Python :: 3.8
Classifier: Programming Language :: Python :: 3.9
Classifier: Programming Language :: Python :: 3.10
Classifier: Programming Language :: Python :: 3.11
Classifier: Programming Language :: Python :: 3.12
Classifier: Programming Language :: Python :: 3.13
Requires-Python: >=3.7
Requires-Dist: toml>=0.10.2
